enre/__init__.py
enre/__main__.py
enre/analysis/__init__.py
enre/analysis/analyze_expr.py
enre/analysis/analyze_manager.py
enre/analysis/analyze_method.py
enre/analysis/analyze_stmt.py
enre/analysis/assign_target.py
enre/analysis/attribute_analyzer.py
enre/analysis/env.py
enre/analysis/error_handler.py
enre/analysis/value_info.py
enre/cfg/HeapObject.py
enre/cfg/Resolver.py
enre/cfg/__init__.py
enre/cfg/call_graph.py
enre/cfg/module_tree.py
enre/dep/DepDB.py
enre/dep/__init__.py
enre/ent/EntKind.py
enre/ent/__init__.py
enre/ent/ent_factory.py
enre/ent/ent_finder.py
enre/ent/entity.py
enre/passes/__init__.py
enre/passes/aggregate_control_flow_info.py
enre/passes/build_ambiguous.py
enre/passes/build_visibility.py
enre/passes/entity_pass.py
enre/ref/Ref.py
enre/ref/__init__.py
enre/test_gen/__init__.py
enre/test_gen/binder.py
enre/test_gen/yaml_represent.py
enre/vis/__init__.py
enre/vis/graphdiffer.py
enre/vis/mapping.py
enre/vis/representation.py
enre/vis/summary_repr.py
enre/vis/und_mapping.py
test/__init__.py
test/branch_def.py
test/class_test.py
test/nested_function.py
test/test.py
test/und_entry.py
xjtu_enre-0.1.0.dist-info/LICENSE
xjtu_enre-0.1.0.dist-info/METADATA
xjtu_enre-0.1.0.dist-info/WHEEL
xjtu_enre-0.1.0.dist-info/top_level.txt
xjtu_enre-0.1.0.dist-info/RECORD
