Metadata-Version: 2.2
Name: xjtu-enre
Version: 0.1.0
Summary: supports the extraction of entities and their dependencies from systems written in multiple languages, enables the customization of dependencies of interest to the user, and makes implicit dependencies explicit.
Home-page: https://github.com/xjtu-enre/ENRE-py.git
Author: xjtu
Author-email: 1811765371@qq.com
Classifier: Programming Language :: Python :: 3
Classifier: License :: OSI Approved :: MIT License
Classifier: Operating System :: OS Independent
Requires-Python: >=3.10
License-File: LICENSE
Requires-Dist: requests>=2.25.1
Dynamic: author
Dynamic: author-email
Dynamic: classifier
Dynamic: description
Dynamic: description-content-type
Dynamic: home-page
Dynamic: requires-dist
Dynamic: requires-python
Dynamic: summary
